{
  "status": "y",
  "d_lang": "eng",
  "title": "Clueless",
  "year": "1995",
  "ua": "U/A 16+",
  "match": "59% match",
  "runtime": "1h 37m",
  "hdsd": "HD",
  "type": "m",
  "creator": "",
  "director": "Amy Heckerling",
  "writer": "Amy Heckerling",
  "short_cast": "Alicia Silverstone, Stacey Dash, Brittany Murphy, Paul Rudd, Donald Faison, Elisa Donovan, Breckin Meyer, Jeremy Sisto, Dan Hedaya, Wallace Shawn, Twink Caplan, Justin Walker, Julie Brown",
  "cast": "Alicia Silverstone, Stacey Dash, Brittany Murphy, Paul Rudd, Donald Faison, Elisa Donovan, Breckin Meyer, Jeremy Sisto, Dan Hedaya, Wallace Shawn, Twink Caplan, Justin Walker, Julie Brown",
  "genre": "Romantic Comedies, US Movies, Teen Movies, Movies Based on Books, Comedies, Romantic Movies",
  "thismovieis": "Charming, Romantic",
  "m_desc": "Suitable for persons aged 16 and above and under parental guidance for people under age of 16",
  "m_reason": "substances",
  "desc": "At a Beverly Hills high school, queen bee Cher excels at makeovers and matchmaking. But figuring out her own love life? Ugh, as if!",
  "oin": "",
  "resume": "",
  "lang": [
    {
      "l": "German",
      "s": "deu"
    },
    {
      "l": "English",
      "s": "eng"
    },
    {
      "l": "Spanish",
      "s": "spa"
    },
    {
      "l": "Spanish",
      "s": "spa"
    },
    {
      "l": "French",
      "s": "fra"
    },
    {
      "l": "Hindi",
      "s": "hin"
    },
    {
      "l": "Italian",
      "s": "ita"
    },
    {
      "l": "Japanese",
      "s": "jpn"
    },
    {
      "l": "Polish",
      "s": "pol"
    },
    {
      "l": "Portuguese",
      "s": "por"
    },
    {
      "l": "Russian",
      "s": "rus"
    },
    {
      "l": "Thai",
      "s": "tha"
    }
  ],
  "episodes": [
    null
  ],
  "suggest": [
    {
      "id": "60034551"
    },
    {
      "id": "80239019"
    },
    {
      "id": "70097579"
    },
    {
      "id": "21304015"
    },
    {
      "id": "80143556"
    },
    {
      "id": "70098895"
    },
    {
      "id": "80217525"
    },
    {
      "id": "80203147"
    },
    {
      "id": "81127150"
    },
    {
      "id": "60036227"
    },
    {
      "id": "80235214"
    },
    {
      "id": "80220496"
    }
  ],
  "error": null
}