{
  "status": "y",
  "d_lang": "hin",
  "title": "Rowdy Rathore",
  "year": "2012",
  "ua": "U/A 18+ [A]",
  "match": "65% match",
  "runtime": "2h 16m",
  "hdsd": "HD",
  "type": "m",
  "creator": "",
  "director": "Prabhu Deva",
  "writer": "Vijayendra Prasad, Shiraz Ahmed",
  "short_cast": "Akshay Kumar, Sonakshi Sinha, Nassar, Yashpal Sharma, Paresh Ganatra, Gurdip Kohli, Mushtaq Khan, Amit Kumar Tiwari",
  "cast": "Akshay Kumar, Sonakshi Sinha, Nassar, Yashpal Sharma, Paresh Ganatra, Gurdip Kohli, Mushtaq Khan, Amit Kumar Tiwari",
  "genre": "Hindi-Language Movies, Bollywood Movies, Action & Adventure, Comedies",
  "thismovieis": "Violent",
  "m_desc": "Content restricted to adults",
  "m_reason": "violence, sexual violence",
  "desc": "A con man uncovers a deadly secret and must save his lady love, the little girl who insists she's his daughter and the small-town locals from the mob.",
  "oin": "",
  "resume": "",
  "lang": [
    {
      "l": "Hindi",
      "s": "hin"
    }
  ],
  "episodes": [
    null
  ],
  "suggest": [
    {
      "id": "81144150"
    },
    {
      "id": "70295762"
    },
    {
      "id": "80057278"
    },
    {
      "id": "70052249"
    },
    {
      "id": "70229046"
    },
    {
      "id": "81244369"
    },
    {
      "id": "80104648"
    },
    {
      "id": "70229498"
    },
    {
      "id": "80017528"
    },
    {
      "id": "70303496"
    },
    {
      "id": "70000196"
    },
    {
      "id": "80091866"
    }
  ],
  "error": null
}