{
  "status": "y",
  "d_lang": "eng",
  "title": "90 Minutes in Heaven",
  "year": "2015",
  "ua": "U/A 16+",
  "match": "35% match",
  "runtime": "2h 1m",
  "hdsd": "HD",
  "type": "m",
  "creator": "",
  "director": "Michael Polish",
  "writer": "Michael Polish, Don Piper, Cecil Murphey",
  "short_cast": "Hayden Christensen, Kate Bosworth, Dwight Yoakam, Michael W. Smith, Fred Thompson, Michael Harding, Marshall Bell, Cynthia Barrett",
  "cast": "Hayden Christensen, Kate Bosworth, Dwight Yoakam, Michael W. Smith, Fred Thompson, Michael Harding, Marshall Bell, Cynthia Barrett",
  "genre": "Drama Movies, Movies Based on Books, Movies Based on Real Life, US Movies",
  "thismovieis": "Inspiring",
  "m_desc": "Suitable for persons aged 16 and above and under parental guidance for people under age of 16",
  "m_reason": "gore",
  "desc": "Some 90 minutes after authorities pronounced him dead at the scene of an accident, a young pastor comes back to life and claims he's been to heaven.",
  "oin": "",
  "resume": "",
  "lang": [
    {
      "l": "German",
      "s": "deu"
    },
    {
      "l": "English",
      "s": "eng"
    },
    {
      "l": "Spanish",
      "s": "spa"
    },
    {
      "l": "Spanish",
      "s": "spa"
    },
    {
      "l": "French",
      "s": "fra"
    },
    {
      "l": "Hindi",
      "s": "hin"
    },
    {
      "l": "Italian",
      "s": "ita"
    },
    {
      "l": "Japanese",
      "s": "jpn"
    },
    {
      "l": "Korean",
      "s": "kor"
    },
    {
      "l": "Polish",
      "s": "pol"
    },
    {
      "l": "Portuguese",
      "s": "por"
    },
    {
      "l": "Turkish",
      "s": "tur"
    }
  ],
  "episodes": [
    null
  ],
  "suggest": [
    {
      "id": "80081151"
    },
    {
      "id": "81341795"
    },
    {
      "id": "81622757"
    },
    {
      "id": "81054619"
    },
    {
      "id": "80200047"
    },
    {
      "id": "81629410"
    },
    {
      "id": "81349306"
    },
    {
      "id": "81298682"
    },
    {
      "id": "81690671"
    },
    {
      "id": "80186829"
    },
    {
      "id": "81435227"
    },
    {
      "id": "81239779"
    }
  ],
  "error": null
}