{
  "status": "y",
  "d_lang": "eng",
  "title": "Nobody Sleeps in the Woods Tonight",
  "year": "2020",
  "ua": "U/A 18+ [A]",
  "match": "71% match",
  "runtime": "1h 43m",
  "hdsd": "HD",
  "type": "m",
  "creator": "",
  "director": "Bartosz M. Kowalski",
  "writer": "Bartosz M. Kowalski, Jan Kwiecinski, Mirella Zaradkiewicz",
  "short_cast": "Julia Wieniawa-Narkiewicz, Micha\u0142 Lupa, Wiktoria G\u0105siewska, Stanis\u0142aw Cywka, Sebastian Dela, Gabriela Muska\u0142a, Micha\u0142 Zbroja, Miros\u0142aw Zbrojewicz, Piotr Cyrwus, Olaf Lubaszenko, Wojciech Mecwaldowski",
  "cast": "Julia Wieniawa-Narkiewicz, Micha\u0142 Lupa, Wiktoria G\u0105siewska, Stanis\u0142aw Cywka, Sebastian Dela, Gabriela Muska\u0142a, Micha\u0142 Zbroja, Miros\u0142aw Zbrojewicz, Piotr Cyrwus, Olaf Lubaszenko, Wojciech Mecwaldowski",
  "genre": "Polish, Horror Movies",
  "thismovieis": "",
  "m_desc": "Content restricted to adults",
  "m_reason": "violence, sex, nudity, gore",
  "desc": "Addicted to technology, a group of teens attends a rehabilitation camp in the forest, but a sinister force there intends to take them offline forever.",
  "oin": "y",
  "resume": "",
  "lang": [
    {
      "l": "German",
      "s": "deu"
    },
    {
      "l": "English",
      "s": "eng"
    },
    {
      "l": "Spanish",
      "s": "spa"
    },
    {
      "l": "Spanish",
      "s": "spa"
    },
    {
      "l": "French",
      "s": "fra"
    },
    {
      "l": "Italian",
      "s": "ita"
    },
    {
      "l": "Polish",
      "s": "pol"
    },
    {
      "l": "Portuguese",
      "s": "por"
    },
    {
      "l": "Turkish",
      "s": "tur"
    }
  ],
  "episodes": [
    null
  ],
  "suggest": [
    {
      "id": "81388045"
    },
    {
      "id": "81483977"
    },
    {
      "id": "70084793"
    },
    {
      "id": "70206131"
    },
    {
      "id": "81325689"
    },
    {
      "id": "81248435"
    },
    {
      "id": "81753224"
    },
    {
      "id": "80217312"
    },
    {
      "id": "81489841"
    },
    {
      "id": "70305901"
    },
    {
      "id": "80198645"
    },
    {
      "id": "81345798"
    }
  ],
  "error": null
}