{
  "status": "y",
  "d_lang": "eng",
  "title": "Ivy + Bean: Doomed to Dance",
  "year": "2021",
  "ua": "U",
  "match": "86% match",
  "runtime": "56m",
  "hdsd": "HD",
  "type": "m",
  "creator": "",
  "director": "Elissa Down",
  "writer": "Annie Barrows, Kathy Waugh",
  "short_cast": "Madison Skye Validum, Keslee Blalock, Jesse Tyler Ferguson, Lidya Jewett, Garfield Wilson, Marci T. House, Jaycie Dotin, Innocent Ekakitie, Mia SwamiNathan, Ava Marchfelder, Roman Pesino, Jesse Gervasi, Claire Smid, Sasha Pieterse",
  "cast": "Madison Skye Validum, Keslee Blalock, Jesse Tyler Ferguson, Lidya Jewett, Garfield Wilson, Marci T. House, Jaycie Dotin, Innocent Ekakitie, Mia SwamiNathan, Ava Marchfelder, Roman Pesino, Jesse Gervasi, Claire Smid, Sasha Pieterse",
  "genre": "Family Features, US Movies, Movies Based on Books, Children & Family Movies, Comedies",
  "thismovieis": "",
  "m_desc": "Suitable for children and persons of all ages",
  "m_reason": "all ages",
  "desc": "Ivy and Bean sign up for ballet, only to learn they'll be dancing in a recital in front of hundreds of people. Time to get out of it \u2014 tout suite!",
  "oin": "y",
  "resume": "",
  "lang": [
    {
      "l": "Arabic",
      "s": "ara"
    },
    {
      "l": "Czech",
      "s": "ces"
    },
    {
      "l": "Danish",
      "s": "dan"
    },
    {
      "l": "German",
      "s": "deu"
    },
    {
      "l": "Greek",
      "s": "ell"
    },
    {
      "l": "English",
      "s": "eng"
    },
    {
      "l": "Spanish",
      "s": "spa"
    },
    {
      "l": "Spanish",
      "s": "spa"
    },
    {
      "l": "Finnish",
      "s": "fin"
    },
    {
      "l": "French",
      "s": "fra"
    },
    {
      "l": "Hebrew",
      "s": "heb"
    },
    {
      "l": "Hindi",
      "s": "hin"
    },
    {
      "l": "Croatian",
      "s": "hrv"
    },
    {
      "l": "Hungarian",
      "s": "hun"
    },
    {
      "l": "Indonesian",
      "s": "ind"
    },
    {
      "l": "Italian",
      "s": "ita"
    },
    {
      "l": "Japanese",
      "s": "jpn"
    },
    {
      "l": "Korean",
      "s": "kor"
    },
    {
      "l": "Malay",
      "s": "msa"
    },
    {
      "l": "Norwegian",
      "s": "nob"
    },
    {
      "l": "Dutch",
      "s": "nld"
    },
    {
      "l": "Polish",
      "s": "pol"
    },
    {
      "l": "Portuguese",
      "s": "por"
    },
    {
      "l": "Portuguese",
      "s": "por"
    },
    {
      "l": "Romanian",
      "s": "ron"
    },
    {
      "l": "Swedish",
      "s": "swe"
    },
    {
      "l": "Tamil",
      "s": "tam"
    },
    {
      "l": "Telugu",
      "s": "tel"
    },
    {
      "l": "Thai",
      "s": "tha"
    },
    {
      "l": "Turkish",
      "s": "tur"
    },
    {
      "l": "Vietnamese",
      "s": "vie"
    },
    {
      "l": "Unknown",
      "s": "und"
    }
  ],
  "episodes": [
    null
  ],
  "suggest": [
    {
      "id": "81338302"
    },
    {
      "id": "81000063"
    },
    {
      "id": "81329721"
    },
    {
      "id": "80994878"
    },
    {
      "id": "81005407"
    },
    {
      "id": "81011712"
    },
    {
      "id": "80993016"
    },
    {
      "id": "80243216"
    },
    {
      "id": "81422413"
    },
    {
      "id": "80222822"
    }
  ],
  "error": null
}