{
  "status": "y",
  "d_lang": "eng",
  "title": "The Cook of Castamar",
  "year": "2021",
  "ua": "U/A 18+ [A]",
  "match": "34% match",
  "runtime": "1 Seasons",
  "hdsd": "HD",
  "type": "t",
  "creator": "",
  "director": "",
  "writer": "",
  "short_cast": "Michelle Jenner, Roberto Enr\u00edquez, Hugo Silva, Maxi Iglesias, Mar\u00eda Herv\u00e1s, Agn\u00e8s Llobet, Paula Usero, Jean Cruz, \u00d3scar Rabad\u00e1n, Fiorella Faltoyano, Nancho Novo, Silvia Abascal, M\u00f3nica L\u00f3pez",
  "cast": "Michelle Jenner, Roberto Enr\u00edquez, Hugo Silva, Maxi Iglesias, Mar\u00eda Herv\u00e1s, Agn\u00e8s Llobet, Paula Usero, Jean Cruz, \u00d3scar Rabad\u00e1n, Fiorella Faltoyano, Nancho Novo, Silvia Abascal, M\u00f3nica L\u00f3pez",
  "genre": "Romantic TV Dramas, Political TV Shows, TV Dramas, Spanish, TV Shows Based on Books, Period Pieces",
  "thismovieis": "Exciting, Romantic",
  "m_desc": "Content restricted to adults",
  "m_reason": "sexual violence, sex, self-harm, nudity",
  "desc": "In 1720 Madrid, a talented cook catches the eye of a widowed duke just as he returns to aristocratic society. Based on the novel by Fernando J. M\u00fa\u00f1ez.",
  "oin": "",
  "season": [
    {
      "s": "1",
      "id": "81354530",
      "ep": "12",
      "sele": " selected"
    }
  ],
  "episodes": [
    {
      "complate": "0",
      "id": "81387441",
      "t": "The Essential Ingredient",
      "s": "S1",
      "ep": "E1",
      "time": "69m"
    },
    {
      "complate": "0",
      "id": "81428034",
      "t": "The Night of the King",
      "s": "S1",
      "ep": "E2",
      "time": "55m"
    },
    {
      "complate": "0",
      "id": "81428035",
      "t": "Credo Ut Intelligam",
      "s": "S1",
      "ep": "E3",
      "time": "57m"
    },
    {
      "complate": "0",
      "id": "81428036",
      "t": "Fly Away",
      "s": "S1",
      "ep": "E4",
      "time": "53m"
    },
    {
      "complate": "0",
      "id": "81428037",
      "t": "The Decision",
      "s": "S1",
      "ep": "E5",
      "time": "52m"
    },
    {
      "complate": "0",
      "id": "81428038",
      "t": "Where No Light Shines",
      "s": "S1",
      "ep": "E6",
      "time": "55m"
    },
    {
      "complate": "0",
      "id": "81428039",
      "t": "So We Are Not Erased",
      "s": "S1",
      "ep": "E7",
      "time": "51m"
    },
    {
      "complate": "0",
      "id": "81428040",
      "t": "What Is Not to Be",
      "s": "S1",
      "ep": "E8",
      "time": "53m"
    },
    {
      "complate": "0",
      "id": "81428041",
      "t": "The Truth",
      "s": "S1",
      "ep": "E9",
      "time": "52m"
    },
    {
      "complate": "0",
      "id": "81428042",
      "t": "What Really Matters",
      "s": "S1",
      "ep": "E10",
      "time": "51m"
    }
  ],
  "nextPageShow": 1,
  "nextPage": 2,
  "nextPageSeason": "81354530",
  "lang": [
    {
      "l": "German",
      "s": "deu"
    },
    {
      "l": "Unknown",
      "s": "und"
    },
    {
      "l": "Spanish",
      "s": "spa"
    },
    {
      "l": "French",
      "s": "fra"
    },
    {
      "l": "Italian",
      "s": "ita"
    },
    {
      "l": "Portuguese",
      "s": "por"
    },
    {
      "l": "Turkish",
      "s": "tur"
    }
  ],
  "last_ep": "81387441",
  "resume": "",
  "suggest": [
    {
      "id": "81222923"
    },
    {
      "id": "80119411"
    },
    {
      "id": "81267689"
    },
    {
      "id": "81414644"
    },
    {
      "id": "80150507"
    },
    {
      "id": "81507021"
    },
    {
      "id": "81410649"
    },
    {
      "id": "80211648"
    },
    {
      "id": "81418071"
    },
    {
      "id": "70285581"
    },
    {
      "id": "948002"
    },
    {
      "id": "80175352"
    }
  ],
  "error": null
}