{
  "status": "y",
  "d_lang": "eng",
  "title": "Firedrake the Silver Dragon",
  "year": "2021",
  "ua": "U/A 7+",
  "match": "54% match",
  "runtime": "1h 33m",
  "hdsd": "HD",
  "type": "m",
  "creator": "",
  "director": "Tomer Eshed",
  "writer": "Cornelia Funke, Johnny Smith",
  "short_cast": "Thomas Brodie-Sangster, Felicity Jones, Freddie Highmore, Patrick Stewart, Meera Syal, Sanjeev Bhaskar, Nonso Anozie",
  "cast": "Thomas Brodie-Sangster, Felicity Jones, Freddie Highmore, Patrick Stewart, Meera Syal, Sanjeev Bhaskar, Nonso Anozie",
  "genre": "Family Features, Movies Based on Books, Children & Family Movies",
  "thismovieis": "",
  "m_desc": "Suitable for children 7 and above and under parental guidance for persons under age of 7",
  "m_reason": "mild language, mild fear",
  "desc": "When his home is threatened by humans, a young dragon summons the courage to seek a mythical paradise where dragons can live in peace and fly free.",
  "oin": "y",
  "resume": "",
  "lang": [
    {
      "l": "Danish",
      "s": "dan"
    },
    {
      "l": "German",
      "s": "deu"
    },
    {
      "l": "English",
      "s": "eng"
    },
    {
      "l": "Spanish",
      "s": "spa"
    },
    {
      "l": "Finnish",
      "s": "fin"
    },
    {
      "l": "French",
      "s": "fra"
    },
    {
      "l": "Hindi",
      "s": "hin"
    },
    {
      "l": "Indonesian",
      "s": "ind"
    },
    {
      "l": "Italian",
      "s": "ita"
    },
    {
      "l": "Japanese",
      "s": "jpn"
    },
    {
      "l": "Malay",
      "s": "msa"
    },
    {
      "l": "Norwegian",
      "s": "nob"
    },
    {
      "l": "Dutch",
      "s": "nld"
    },
    {
      "l": "Portuguese",
      "s": "por"
    },
    {
      "l": "Swedish",
      "s": "swe"
    }
  ],
  "episodes": [
    null
  ],
  "suggest": [
    {
      "id": "81354554"
    },
    {
      "id": "81050165"
    },
    {
      "id": "81018682"
    },
    {
      "id": "81159137"
    },
    {
      "id": "81381727"
    },
    {
      "id": "80245121"
    },
    {
      "id": "80161029"
    },
    {
      "id": "80234520"
    },
    {
      "id": "81487903"
    },
    {
      "id": "81002813"
    },
    {
      "id": "80195962"
    },
    {
      "id": "81153694"
    }
  ],
  "error": null
}