{
  "status": "y",
  "d_lang": "kan",
  "title": "Jana 2022 (Kannada)",
  "year": "2022",
  "ua": "U/A 13+",
  "match": "62% match",
  "runtime": "2h 41m",
  "hdsd": "HD",
  "type": "m",
  "creator": "",
  "director": "Dijo Jose Antony",
  "writer": "Sharis Mohammed",
  "short_cast": "Prithviraj Sukumaran, Suraj Venjaramoodu, Pasupathi Raj, G.M. Sundar, Mamtha Mohandas, Sri Divya, Shari, Priyanka Nair, Vaishnavi Venugopal, Vincy Aloshious",
  "cast": "Prithviraj Sukumaran, Suraj Venjaramoodu, Pasupathi Raj, G.M. Sundar, Mamtha Mohandas, Sri Divya, Shari, Priyanka Nair, Vaishnavi Venugopal, Vincy Aloshious",
  "genre": "Dramas, Courtroom Movies",
  "thismovieis": "",
  "m_desc": "Suitable for persons aged 13 and above and under parental guidance for people under age of 13",
  "m_reason": "violence, threat, mature themes, gore",
  "desc": "As a college professor's brutal murder sparks student unrest, a cop launches an investigation while a lawyer seeks justice in the courtroom.",
  "oin": "",
  "resume": "",
  "lang": [
    {
      "l": "Kannada",
      "s": "kan"
    }
  ],
  "episodes": [
    null
  ],
  "suggest": [
    {
      "id": "81477034"
    },
    {
      "id": "81611931"
    },
    {
      "id": "81555342"
    },
    {
      "id": "81609575"
    },
    {
      "id": "81753409"
    },
    {
      "id": "81519046"
    },
    {
      "id": "81681254"
    },
    {
      "id": "81729007"
    },
    {
      "id": "81508706"
    },
    {
      "id": "81637263"
    },
    {
      "id": "81690671"
    },
    {
      "id": "81508710"
    }
  ],
  "error": null
}