{
  "status": "y",
  "d_lang": "eng",
  "title": "Rebel Moon \u2014 Part Two: The Scargiver",
  "year": "2024",
  "ua": "U/A 13+",
  "match": "91% match",
  "runtime": "2h 3m",
  "hdsd": "HD",
  "type": "m",
  "creator": "",
  "director": "Zack Snyder",
  "writer": "Zack Snyder, Kurt Johnstad, Shay Hatten",
  "short_cast": "Sofia Boutella, Djimon Hounsou, Ed Skrein, Anthony Hopkins, Michiel Huisman, Doona Bae, Ray Fisher, Staz Nair, Fra Fee, Cleopatra Coleman, Stuart Martin, Ingvar Sigur\u00f0sson, Alfonso Herrera, Cary Elwes, Rhian Rees, Elise Duffy, Sky Yang, Charlotte Maggi",
  "cast": "Sofia Boutella, Djimon Hounsou, Ed Skrein, Anthony Hopkins, Michiel Huisman, Doona Bae, Ray Fisher, Staz Nair, Fra Fee, Cleopatra Coleman, Stuart Martin, Ingvar Sigur\u00f0sson, Alfonso Herrera, Cary Elwes, Rhian Rees, Elise Duffy, Sky Yang, Charlotte Maggi",
  "genre": "Sci-Fi Movies, Action & Adventure Movies, US Movies",
  "thismovieis": "Imaginative, Exciting",
  "m_desc": "Suitable for persons aged 13 and above and under parental guidance for people under age of 13",
  "m_reason": "violence, threat, mature themes, language",
  "desc": "The rebels gear up for battle against the ruthless forces of the Motherworld as unbreakable bonds are forged, heroes emerge \u2014 and legends are made.",
  "oin": "y",
  "resume": "",
  "lang": [
    {
      "l": "Czech",
      "s": "ces"
    },
    {
      "l": "Czech",
      "s": "ces"
    },
    {
      "l": "German",
      "s": "deu"
    },
    {
      "l": "English",
      "s": "eng"
    },
    {
      "l": "Spanish",
      "s": "spa"
    },
    {
      "l": "Spanish",
      "s": "spa"
    },
    {
      "l": "Filipino (Tagalog)",
      "s": "fil"
    },
    {
      "l": "French",
      "s": "fra"
    },
    {
      "l": "Hindi",
      "s": "hin"
    },
    {
      "l": "Hungarian",
      "s": "hun"
    },
    {
      "l": "Indonesian",
      "s": "ind"
    },
    {
      "l": "Italian",
      "s": "ita"
    },
    {
      "l": "Japanese",
      "s": "jpn"
    },
    {
      "l": "Unknown",
      "s": "und"
    },
    {
      "l": "Unknown",
      "s": "und"
    },
    {
      "l": "Portuguese",
      "s": "por"
    },
    {
      "l": "Tamil",
      "s": "tam"
    },
    {
      "l": "Telugu",
      "s": "tel"
    },
    {
      "l": "Thai",
      "s": "tha"
    },
    {
      "l": "Turkish",
      "s": "tur"
    },
    {
      "l": "Ukrainian",
      "s": "ukr"
    },
    {
      "l": "Vietnamese",
      "s": "vie"
    }
  ],
  "episodes": [
    null
  ],
  "suggest": [
    {
      "id": "81464239"
    },
    {
      "id": "81094067"
    },
    {
      "id": "81199139"
    },
    {
      "id": "81696507"
    },
    {
      "id": "81012048"
    },
    {
      "id": "81465109"
    },
    {
      "id": "81480320"
    },
    {
      "id": "80216309"
    },
    {
      "id": "81183713"
    },
    {
      "id": "80098200"
    },
    {
      "id": "81416258"
    },
    {
      "id": "81762621"
    }
  ],
  "error": null
}