{
  "status": "y",
  "d_lang": "tel",
  "title": "Three (Telugu)",
  "year": "2012",
  "ua": "U/A 16+",
  "match": "47% match",
  "runtime": "2h 26m",
  "hdsd": "HD",
  "type": "m",
  "creator": "",
  "director": "Aishwarya Dhanush",
  "writer": "Aishwarya Dhanush",
  "short_cast": "Dhanush, Shruthi Haasan, Sunder Ramu, Sivakarthikeyan, Prabhu, Rohini",
  "cast": "Dhanush, Shruthi Haasan, Sunder Ramu, Sivakarthikeyan, Prabhu, Rohini",
  "genre": "Dramas, Romantic Movies, Tamil-Language Movies",
  "thismovieis": "Dark, Romantic",
  "m_desc": "Suitable for persons aged 16 and above and under parental guidance for people under age of 16",
  "m_reason": "suicide, self-harm, mature themes",
  "desc": "After her husband\u2019s unnatural death, a young widow in search of answers discovers a secret diagnosis and a world of hidden suffering and sacrifice.",
  "oin": "",
  "resume": "",
  "lang": [
    {
      "l": "Telugu",
      "s": "tel"
    }
  ],
  "episodes": [
    null
  ],
  "suggest": [
    {
      "id": "80203159"
    },
    {
      "id": "81642992"
    },
    {
      "id": "80187471"
    },
    {
      "id": "81588444"
    },
    {
      "id": "80170125"
    },
    {
      "id": "80190101"
    },
    {
      "id": "81690671"
    },
    {
      "id": "81582584"
    },
    {
      "id": "81176205"
    },
    {
      "id": "81486768"
    },
    {
      "id": "80147949"
    },
    {
      "id": "81052266"
    }
  ],
  "error": null
}